{
    "list": [
        {
            "id": "1",
            "name": "Alnes fyr",
            "latitude": "62.490408",
            "longitude": "5.962346",
            "description": "Steinstrand",
            "deep_description": "Dette er en steinstrand med store steiner. Her er det parkeringsmuligheter og cafe rett i nærheten. Det er lang vei til nærmeste overnattingssted"
        },
        {
            "id": "2",
            "name": "Berlevåg Sandfjorden",
            "latitude": "70.798719",
            "longitude": "29.26487",
            "description": "Sandstrand",
            "deep_description": "Dette er en liten sandstrand. Det er lang vei til butikk og nærmeste overnattingssted "
        },
        {
            "id": "3",
            "name": "Boresanden",
            "latitude": "58.8007305",
            "longitude": "5.5483482",
            "description": "Sandstrand",
            "deep_description": "Dette er en lang sandstrand. Her holder Bore surfeskole til. De tilbyr kurs samt leie av utstyr. Her er det ingen matbutikk eller overnattingssted i nærheten. "
        },
        {
            "id": "4",
            "name": "Brusand",
            "latitude": "58.534152",
            "longitude": "5.754511",
            "description": "Sandstrand",
            "deep_description": "Dette er en lang sandstrand med Ogna camping like i nærheten. Her er det lang vei til butikken"
        },
        {
            "id": "5",
            "name": "Ducks",
            "latitude": "69.068591",
            "longitude": "15.525122",
            "description": "Steinete strand",
            "deep_description": "Her går man ut fra steiner. Det er lang vei til nærmeste matbutikk og overnattingssted "
        },
        {
            "id": "6",
            "name": "Ervik",
            "latitude": "62.1664637",
            "longitude": "5.1148224",
            "description": "Sandstrand",
            "deep_description": "Dette er en liten sandstrand. Erviksanden camping ligger like i nærheten. Her er det lang vei til butikken "
        },
        {
            "id": "7",
            "name": "Farstadstranden",
            "latitude": "62.98273",
            "longitude": "7.152414",
            "description": "Sandstrand",
            "deep_description": "Dette er en liten sandstrand. Her er det parkeringsplass rett i nærheten. Det lang vei til butikken og nærmeste overnattingssted "
        },
        {
            "id": "8",
            "name": "Fløstranda",
            "latitude": "62.3867226",
            "longitude": "5.8304103",
            "description": "Skjær",
            "deep_description": "Her går man ut fra skjær. Det er lang vei til butikk og nærmeste overnattingssted "
        },
        {
            "id": "9",
            "name": "G-force",
            "latitude": "68.63866",
            "longitude": "14.432433",
            "description": "Steinstrand",
            "deep_description": "Her går man ut fra skjær. Det er lang vei til butikk og nærmeste overnattingssted "
        },
        {
            "id": "10",
            "name": "Havik Strand",
            "latitude": "58.067319",
            "longitude": "6.727291",
            "description": "Surfeskole/utleie",
            "deep_description": "Dette er en lang sandstrand. Her holder Lista Surfing til. De tilbyr kurs og utleie. Det er lang vei til butikken og nærmeste overnattingssted "
        },
        {
            "id": "11",
            "name": "Hellestøstranden",
            "latitude": "58.84114",
            "longitude": "5.56069",
            "description": "Surfeskole/utleie",
            "deep_description": "Dette er en lang sandstrand. Her holder surfschool til. De tilbyr kurs og utleie. Det er lang vei til nærmeste butikken og overnattingssted "
        },
        {
            "id": "12",
            "name": "Hemnesvika, Karmøy",
            "latitude": "59.199336",
            "longitude": "5.180888",
            "description": "Sandstrand",
            "deep_description": "Dette er en liten sandstrand. Her er det lang vei til butikken og overnattingssted"
        },
        {
            "id": "13",
            "name": "Hoddevik",
            "latitude": "62.12357",
            "longitude": "5.161162",
            "description": "Surfeskole/utleie",
            "deep_description": "Dette er en en lang sandstrand. Her holder surfeskolen lapoint til. De tilbyr overnatting med mat"
        },
        {
            "id": "14",
            "name": "Kvassheim",
            "latitude": "58.549514",
            "longitude": "5.675106",
            "description": "Steinstrand",
            "deep_description": "Her får man ut fra en steinete strand. Det er lang vei til nærmeste matbutikk og overnattingssted "
        },
        {
            "id": "15",
            "name": "Langeby",
            "latitude": "59.07789",
            "longitude": "10.261781",
            "description": "Sandstrand",
            "deep_description": "Dette er en liten sandstrand. Langeby camping ligger like i nærheten. Det er lang vei til nærmeste matbutikk"
        },
        {
            "id": "16",
            "name": "Løpsvika",
            "latitude": "67.324",
            "longitude": "14.480065",
            "description": "Sandstrand",
            "deep_description": "Dette er en lang sandstrand. Her er det langt til nærmeste matbutikk og overnattingssted"
        },
        {
            "id": "17",
            "name": "Melandsjøen",
            "latitude": "66.948197",
            "longitude": "13.741238",
            "description": "Skjær",
            "deep_description": "Her går man ut fra skjær. Det er lang vei til butikk og nærmeste overnattingssted "
        },
        {
            "id": "18",
            "name": "Midtfløsanden",
            "latitude": "62.406185",
            "longitude": "5.85119",
            "description": "Sandstrand",
            "deep_description": "Dette er liten sandstrand. Flø feriesenter ligger like i nærheten. Det er lang vei til nærmeste matbutikk"
        },
        {
            "id": "19",
            "name": "Naverfjorden",
            "latitude": "58.981309",
            "longitude": "9.98176",
            "description": "Ut fra steinete molo",
            "deep_description": "Her går man ut fra en molo. Det er lang vei til butikk og nærmeste overnattingssted "
        },
        {
            "id": "20",
            "name": "Persfjord",
            "latitude": "70.4201376",
            "longitude": "30.7908117",
            "description": "Liten sandstrand",
            "deep_description": "Dette er en lang sandstrand. Det er lang vei til butikk og nærmeste overnattingssted "
        },
        {
            "id": "21",
            "name": "Point Perfect, Skeiestranda, Orre",
            "latitude": "58.697549",
            "longitude": "5.539877",
            "description": "Steinstrand",
            "deep_description": "Dette er en lang sandstrand. Skeieparken camping ligger like i nærheten, men det er lang veil til nærmeste matbutikk"
        },
        {
            "id": "22",
            "name": "Porsangvika",
            "latitude": "70.874129",
            "longitude": "25.8613508",
            "description": "Sandstrand",
            "deep_description": "Dette er en lang sandstrand. Her er det langt til nærmeste matbutikk og overnattingssted"
        },
        {
            "id": "23",
            "name": "Refsnesstranda",
            "latitude": "58.68748",
            "longitude": "5.551086",
            "description": "Sandstrand",
            "deep_description": "Dette er en lang sandstrand. Skeieparken camping ligger like i nærheten, men det er lang vei til nærmeste matbutikk"
        },
        {
            "id": "24",
            "name": "Revesanden",
            "latitude": "58.757476",
            "longitude": "5.495469",
            "description": "Sandstrand",
            "deep_description": "Dette er en lang sandstrand. Reveparken camping ligger like i nærheten, men det er lang vei til nærmeste matbutikk"
        },
        {
            "id": "25",
            "name": "Saltstein",
            "latitude": "58.966499",
            "longitude": "9.850051",
            "description": "Steinstrand",
            "deep_description": "Dette er en steinstrand med store steiner. Det er lang vei til butikk og nærmeste overnattingssted "
        },
        {
            "id": "26",
            "name": "Saltstraumen",
            "latitude": "67.203201",
            "longitude": "14.358142",
            "description": "Sandstrand",
            "deep_description": "Dette er en lang sandstrand. Det er lang vei til butikk og nærmeste overnattingssted "
        },
        {
            "id": "27",
            "name": "Sandvika badestrand, \"The Frog\"",
            "latitude": "68.756938",
            "longitude": "14.473932",
            "description": "Sandstrand",
            "deep_description": "Dette er en kort sandstrand. Det er lang vei til butikk og nærmeste overnattingssted "
        },
        {
            "id": "28",
            "name": "Selestranden",
            "latitude": "58.8159795",
            "longitude": "5.541879",
            "description": "Steinstrand",
            "deep_description": "Dette er en lang sandstrand. Havblikk camping ligger like i nærheten, men det er lang vei til nærmeste matbutikk"
        },
        {
            "id": "29",
            "name": "Sjøstranda",
            "latitude": "58.019977",
            "longitude": "7.448316",
            "description": "Sandstrand",
            "deep_description": "Dette er en lang sandstrand. Topcamp og sjøsanden ferietun ligger like i nærheten. Det er også kort vei til nærmeste matbutikk"
        },
        {
            "id": "30",
            "name": "Skallavoldbukta",
            "latitude": "59.292554",
            "longitude": "10.502219",
            "description": "Sandstrand",
            "deep_description": "Dette er en lang sandstrand. Her ligger skallavold camping rett i nærheten. Det er lang vei til nærmeste matbutikk"
        },
        {
            "id": "31",
            "name": "Skallelv",
            "latitude": "70.188634",
            "longitude": "30.347314",
            "description": "Sandstrand",
            "deep_description": "Dette er en kort sandstrand. Det er lang vei til butikk og nærmeste overnattingssted "
        },
        {
            "id": "32",
            "name": "Solastranden",
            "latitude": "58.887373",
            "longitude": "5.601266",
            "description": "Surfeskole/utleie",
            "deep_description": "Dette er en lang sandstrand. Her holder surfschool til. De tilbyr kurs og utleie. Her er det kiosk og hotell rett i nærheten"
        },
        {
            "id": "33",
            "name": "Storesand",
            "latitude": "59.025138",
            "longitude": "11.017506",
            "description": "Sandstrand",
            "deep_description": "Dette er en kort sandstrand. Det er lang vei til butikk og nærmeste overnattingssted "
        },
        {
            "id": "34",
            "name": "Unstadstranden",
            "latitude": "68.2687586",
            "longitude": "13.5810711",
            "description": "Surfeskole/utleie",
            "deep_description": "Dette er en lang sandstrand. Her holder Lofoten surfesenter til. De tilbyr kurs og utleie av utstyr. Unstad Arctic Surf ligger rett i nærheten og tilbyr overnatting. Det er lang vei til nærmeste matbutikk. "
        },
        {
            "id": "35",
            "name": "Vøra",
            "latitude": "59.072399",
            "longitude": "10.259077",
            "description": "Sandstrand",
            "deep_description": "Dette er en lang sandstrand. Vøra camping ligger like i nærheten, men det er lang vei til nærmeste matbutikk"
        }
    ]
}